proxmox_hetzner_autoconfigure/configurators/__init__.py
proxmox_hetzner_autoconfigure/configurators/backup/backup.py
proxmox_hetzner_autoconfigure/configurators/backup/template.jinja2
proxmox_hetzner_autoconfigure/configurators/configurator.py
proxmox_hetzner_autoconfigure/configurators/network/network.py
proxmox_hetzner_autoconfigure/configurators/network/topologies/routed_separate_ips.jinja2
proxmox_hetzner_autoconfigure/configurators/network/topologies/routed_separate_ips.py
proxmox_hetzner_autoconfigure/configurators/network/topologies/routed_subnet.jinja2
proxmox_hetzner_autoconfigure/configurators/network/topologies/routed_subnet.py
proxmox_hetzner_autoconfigure/configurators/network/topologies/routed_wrapper.jinja2
proxmox_hetzner_autoconfigure/configurators/snippets/dnsmasq.jinja2
proxmox_hetzner_autoconfigure/configurators/snippets/dnsmasq.toml
proxmox_hetzner_autoconfigure/configurators/snippets/lvm_thin.jinja2
proxmox_hetzner_autoconfigure/configurators/snippets/lvm_thin.toml
proxmox_hetzner_autoconfigure/configurators/snippets/security.jinja2
proxmox_hetzner_autoconfigure/configurators/snippets/security.toml
proxmox_hetzner_autoconfigure/configurators/snippets/snippets.py
proxmox_hetzner_autoconfigure/configurators/snippets/template.jinja2
proxmox_hetzner_autoconfigure/configurators/storage_box/storage_box.py
proxmox_hetzner_autoconfigure/configurators/storage_box/template.jinja2
proxmox_hetzner_autoconfigure/configurators/tls/template.jinja2
proxmox_hetzner_autoconfigure/configurators/tls/tls.py
proxmox_hetzner_autoconfigure/configurators/wireguard/template.jinja2
proxmox_hetzner_autoconfigure/configurators/wireguard/wireguard.py
proxmox_hetzner_autoconfigure/main.py
proxmox_hetzner_autoconfigure/next-steps.jinja2
proxmox_hetzner_autoconfigure/util/heredoc.jinja2
proxmox_hetzner_autoconfigure/util/install.jinja2
proxmox_hetzner_autoconfigure/util/util.py
proxmox_hetzner_autoconfigure-0.2.0.dist-info/entry_points.txt
proxmox_hetzner_autoconfigure-0.2.0.dist-info/WHEEL
proxmox_hetzner_autoconfigure-0.2.0.dist-info/METADATA
proxmox_hetzner_autoconfigure-0.2.0.dist-info/RECORD
