Metadata-Version: 2.1
Name: proxmox-hetzner-autoconfigure
Version: 0.2.0
Summary: Helps to configure Proxmox on Hetzner. Takes over where Hetzner installimage left off
Author: John Knott
Author-email: john.knott@gmail.com
Requires-Python: >=3.6,<4.0
Classifier: Programming Language :: Python :: 3
Classifier: Programming Language :: Python :: 3.6
Classifier: Programming Language :: Python :: 3.7
Classifier: Programming Language :: Python :: 3.8
Classifier: Programming Language :: Python :: 3.9
Requires-Dist: ipdb (>=0.13.3,<0.14.0)
Requires-Dist: jinja2 (>=2.11.2,<3.0.0)
Requires-Dist: pythondialog (>=3.5.1,<4.0.0)
Requires-Dist: toml (>=0.10.1,<0.11.0)
